katsdpmodels/__init__.py
katsdpmodels/band_mask.py
katsdpmodels/models.py
katsdpmodels/primary_beam.py
katsdpmodels/py.typed
katsdpmodels/rfi_mask.py
katsdpmodels/fetch/__init__.py
katsdpmodels/fetch/aiohttp.py
katsdpmodels/fetch/requests.py
katsdpmodels-0.3.dist-info/LICENSE
katsdpmodels-0.3.dist-info/METADATA
katsdpmodels-0.3.dist-info/WHEEL
katsdpmodels-0.3.dist-info/top_level.txt
katsdpmodels-0.3.dist-info/RECORD
