Metadata-Version: 2.1
Name: katsdpmodels
Version: 0.3
Summary: Interfaces to access models used in MeerKAT SDP
Home-page: https://github.com/ska-sa/katsdpmodels
Author: MeerKAT SDP Team
Author-email: sdpdev+katsdpmodels@ska.ac.za
License: Modified BSD
Platform: UNKNOWN
Classifier: License :: OSI Approved :: BSD License
Classifier: Programming Language :: Python
Classifier: Programming Language :: Python :: 3
Classifier: Topic :: Scientific/Engineering :: Astronomy
Requires-Python: >=3.6
Requires-Dist: astropy
Requires-Dist: h5py (>=2.9)
Requires-Dist: numba
Requires-Dist: numpy
Requires-Dist: scipy
Requires-Dist: strict-rfc3339
Requires-Dist: typing-extensions
Provides-Extra: aiohttp
Requires-Dist: aiohttp ; extra == 'aiohttp'
Requires-Dist: aiohttp-retry (>=2.3) ; extra == 'aiohttp'
Provides-Extra: doc
Requires-Dist: sphinx ; extra == 'doc'
Requires-Dist: sphinxcontrib-tikz ; extra == 'doc'
Requires-Dist: sphinx-rtd-theme ; extra == 'doc'
Provides-Extra: requests
Requires-Dist: requests ; extra == 'requests'
Provides-Extra: test
Requires-Dist: aioresponses ; extra == 'test'
Requires-Dist: katsdptelstate[aio] ; extra == 'test'
Requires-Dist: pytest ; extra == 'test'
Requires-Dist: pytest-asyncio ; extra == 'test'
Requires-Dist: pytest-mock ; extra == 'test'
Requires-Dist: responses ; extra == 'test'
Requires-Dist: tornado ; extra == 'test'
